input/project_list.xlsx
installation_instructions/01_windows_anaconda_prompt_menu.png
installation_instructions/02_make_folders.png
installation_instructions/03_clone_the_repo.png
installation_instructions/05_download_zip.png
installation_instructions/06_landbosse_dev.png
installation_instructions/11_copy_project_input_template.png
installation_instructions/12_paste_project_input_template.png
installation_instructions/13_done_pasting.png
installation_instructions/macos_developer.md
installation_instructions/normal-operation-flowchart.png
installation_instructions/operation_and_folder_structure.md
installation_instructions/validation-flowchart.png
installation_instructions/windows_end_user.md
landbosse/__init__.py
landbosse/landbosse_runner.py
landbosse/excelio/CsvGenerator.py
landbosse/excelio/GridSearchTree.py
landbosse/excelio/WeatherWindowCSVReader.py
landbosse/excelio/XlsxDataframeCache.py
landbosse/excelio/XlsxFileOperations.py
landbosse/excelio/XlsxGenerator.py
landbosse/excelio/XlsxManagerRunner.py
landbosse/excelio/XlsxOperationException.py
landbosse/excelio/XlsxParallelManagerRunner.py
landbosse/excelio/XlsxReader.py
landbosse/excelio/XlsxSerialManagerRunner.py
landbosse/excelio/XlsxValidator.py
landbosse/excelio/__init__.py
landbosse/landbosse_omdao/CsvGenerator.py
landbosse/landbosse_omdao/GridSearchTree.py
landbosse/landbosse_omdao/OpenMDAODataframeCache.py
landbosse/landbosse_omdao/WeatherWindowCSVReader.py
landbosse/landbosse_omdao/XlsxOperationException.py
landbosse/landbosse_omdao/XlsxValidator.py
landbosse/landbosse_omdao/__init__.py
landbosse/landbosse_omdao/landbosse.py
landbosse/model/CollectionCost.py
landbosse/model/CostModule.py
landbosse/model/DefaultMasterInputDict.py
landbosse/model/DevelopmentCost.py
landbosse/model/ErectionCost.py
landbosse/model/FoundationCost.py
landbosse/model/GridConnectionCost.py
landbosse/model/ManagementCost.py
landbosse/model/Manager.py
landbosse/model/SitePreparationCost.py
landbosse/model/SubstationCost.py
nrel_landbosse-2.6.1.dist-info/licenses/LICENSE.txt
nrel_landbosse-2.6.1.dist-info/METADATA
nrel_landbosse-2.6.1.dist-info/WHEEL
nrel_landbosse-2.6.1.dist-info/top_level.txt
nrel_landbosse-2.6.1.dist-info/RECORD
