Metadata-Version: 2.4
Name: NREL-landbosse
Version: 2.6.1
Summary: Wind-Plant Integrated System Design & Engineering Model
Author-email: NREL WISDEM Team <systems.engineering@nrel.gov>
Maintainer-email: NREL WISDEM Team <systems.engineering@nrel.gov>
License: Apache-2.0
Project-URL: Homepage, https://github.com/WISDEM/LandBOSSE
Project-URL: Project, https://www.nrel.gov/wind/systems-engineering.html
Keywords: wind,turbine,mdao,design,optimization
Classifier: Development Status :: 4 - Beta
Classifier: Intended Audience :: Science/Research
Classifier: Topic :: Scientific/Engineering
Classifier: License :: OSI Approved :: Apache Software License
Classifier: Programming Language :: Python :: 3
Classifier: Programming Language :: Python :: 3.9
Classifier: Programming Language :: Python :: 3.10
Classifier: Programming Language :: Python :: 3.11
Classifier: Programming Language :: Python :: 3.12
Classifier: Programming Language :: Python :: 3 :: Only
Classifier: Programming Language :: C
Classifier: Programming Language :: Fortran
Requires-Python: >=3.9
License-File: LICENSE.txt
Requires-Dist: numpy
Requires-Dist: openpyxl
Requires-Dist: pandas
Requires-Dist: scipy
Requires-Dist: xlsxwriter
Provides-Extra: test
Requires-Dist: coveralls; extra == "test"
Requires-Dist: pytest; extra == "test"
Provides-Extra: docs
Requires-Dist: sphinx; extra == "docs"
Requires-Dist: sphinx_rtd_theme; extra == "docs"
Dynamic: license-file
